{
    "AS_Button_c2047bf9d76e4e828b9eae18759a44f0": {
        "id": "AS_Button_c2047bf9d76e4e828b9eae18759a44f0",
        "type": "ACTION_SEQUENCE",
        "params": [{
            "datatype": "collection",
            "name": "eventobject"
        }],
        "contextObj": {
            "name": "Form1",
            "type": "forms",
            "platform": null,
            "KUID": "he16c5c508ed4892b27ba3c5bbae8ed8"
        },
        "language": "js",
        "actions": [{
            "id": "IF_CONDITION__hfc6c4aeaa814d3e9f73268558d17491",
            "type": "IF_CONDITION",
            "conditions": [{
                "leftValueType": "varvalue",
                "leftValue": "switchState",
                "operator": "===",
                "rightValueType": "value",
                "rightValue": "false"
            }],
            "parentId": null,
            "callbackType": null,
            "criteria": "all"
        }, {
            "id": "IF_CONDITION__ed633b01a40c4c4aa836a973c9430792",
            "type": "ELSE_IF_CONDITION",
            "conditions": [{
                "leftValueType": "varvalue",
                "leftValue": "switchState",
                "operator": "===",
                "rightValueType": "value",
                "rightValue": "true"
            }],
            "parentId": null,
            "callbackType": null,
            "criteria": "all"
        }, {
            "id": "ADD_SNIPPET__e84043b3f4cc4c35bbb502e2a25f3ca7",
            "type": "ADD_SNIPPET",
            "codeSnippet": "if(switchState == false) {\n  turnLightOn();\n}\nelse if(switchState == true) {\n  turnLightOff();\n}",
            "parentId": null,
            "callbackType": null
        }, {
            "id": "SET_FORM_WIDGET_PROPERTY_Untitled___b46dc855c2bf415388f69bb8136f6aff",
            "type": "SET_WIDGET_PROPERTY",
            "itemType": "FORM",
            "itemId": "Form1",
            "propertyName": "text",
            "propertyValue": "ON",
            "itemKUID": "he16c5c508ed4892b27ba3c5bbae8ed8",
            "widgetKUID": "a979695265684b56ad2663b897c50c7b",
            "isSkinProperty": false,
            "wType": "Button",
            "forkedPlatform": "all",
            "parentId": "IF_CONDITION__hfc6c4aeaa814d3e9f73268558d17491",
            "callbackType": null
        }, {
            "id": "SET_FORM_WIDGET_PROPERTY____c6157f7355064f61813c74cc284e7c97",
            "type": "SET_WIDGET_PROPERTY",
            "itemType": "FORM",
            "itemId": "Form1",
            "propertyName": "skin",
            "propertyValue": "ONskin",
            "itemKUID": "he16c5c508ed4892b27ba3c5bbae8ed8",
            "widgetKUID": "a979695265684b56ad2663b897c50c7b",
            "skinKUID": "sf9f7814449948de806eb089231de856",
            "isSkinProperty": true,
            "wType": "Button",
            "currentTheme": "defaultTheme",
            "forkedPlatform": "all",
            "parentId": "IF_CONDITION__hfc6c4aeaa814d3e9f73268558d17491",
            "callbackType": null
        }, {
            "id": "SET_FORM_WIDGET_PROPERTY____ff21e1636bad41d99b603922da34e204",
            "type": "SET_WIDGET_PROPERTY",
            "itemType": "FORM",
            "itemId": "Form1",
            "propertyName": "text",
            "propertyValue": "OFF",
            "itemKUID": "he16c5c508ed4892b27ba3c5bbae8ed8",
            "widgetKUID": "a979695265684b56ad2663b897c50c7b",
            "isSkinProperty": false,
            "wType": "Button",
            "forkedPlatform": "all",
            "parentId": "IF_CONDITION__ed633b01a40c4c4aa836a973c9430792",
            "callbackType": null
        }, {
            "id": "SET_FORM_WIDGET_PROPERTY____fc2996ea6bef4929aa7bff59d2680063",
            "type": "SET_WIDGET_PROPERTY",
            "itemType": "FORM",
            "itemId": "Form1",
            "widgetId": "ONoff2",
            "propertyName": "skin",
            "propertyValue": "OFFskin",
            "itemKUID": "he16c5c508ed4892b27ba3c5bbae8ed8",
            "widgetKUID": "d963720f267a4c3991d1b09c521059bc",
            "skinKUID": "sb994112b45f4397b4e397f086b84a07",
            "isSkinProperty": true,
            "wType": "Button",
            "currentTheme": "defaultTheme",
            "forkedPlatform": "all",
            "parentId": "IF_CONDITION__ed633b01a40c4c4aa836a973c9430792",
            "callbackType": null,
            "widgetPath": "this.view.ONoff2"
        }]
    }
}